rnow/__init__.py
rnow/__main__.py
rnow/models.py
rnow/cli/__init__.py
rnow/cli/auth.py
rnow/cli/blob.py
rnow/cli/commands.py
rnow/cli/common.py
rnow/cli/cube.py
rnow/cli/main.py
rnow/cli/test.py
rnow/cli/token_count.py
rnow/cli/upload.py
rnow/core/__init__.py
rnow/core/reward.py
rnow/core/tool.py
rnow/templates/deepseek-aha/config.yml
rnow/templates/deepseek-aha/rewards.py
rnow/templates/deepseek-aha/train.jsonl
rnow/templates/finqa/README.md
rnow/templates/finqa/config.yml
rnow/templates/finqa/requirements.txt
rnow/templates/finqa/rewards.py
rnow/templates/finqa/train.jsonl
rnow/templates/food-extract/README.md
rnow/templates/food-extract/config.yml
rnow/templates/food-extract/rewards.py
rnow/templates/food-extract/setup.py
rnow/templates/food-extract/train.jsonl
rnow/templates/food-extract/images/00000.png
rnow/templates/food-extract/images/00001.png
rnow/templates/mcp-tavily/config.yml
rnow/templates/mcp-tavily/requirements.txt
rnow/templates/mcp-tavily/rewards.py
rnow/templates/mcp-tavily/train.jsonl
rnow/templates/new/config.yml
rnow/templates/new/requirements.txt
rnow/templates/new/rewards.py
rnow/templates/new/train.jsonl
rnow/templates/rl-nextjs/config.yml
rnow/templates/rl-nextjs/requirements.txt
rnow/templates/rl-nextjs/rewards.py
rnow/templates/rl-nextjs/train.jsonl
rnow/templates/rl-single/config.yml
rnow/templates/rl-single/requirements.txt
rnow/templates/rl-single/rewards.py
rnow/templates/rl-single/train.jsonl
rnow/templates/rl-tools/config.yml
rnow/templates/rl-tools/requirements.txt
rnow/templates/rl-tools/rewards.py
rnow/templates/rl-tools/tools.py
rnow/templates/rl-tools/train.jsonl
rnow/templates/sft/config.yml
rnow/templates/sft/train.jsonl
rnow/templates/tutorial-reward/config.yml
rnow/templates/tutorial-reward/requirements.txt
rnow/templates/tutorial-reward/rewards.py
rnow/templates/tutorial-reward/train.jsonl
rnow/templates/tutorial-tool/config.yml
rnow/templates/tutorial-tool/requirements.txt
rnow/templates/tutorial-tool/rewards.py
rnow-0.3.17.dist-info/licenses/LICENSE
rnow-0.3.17.dist-info/METADATA
rnow-0.3.17.dist-info/WHEEL
rnow-0.3.17.dist-info/entry_points.txt
rnow-0.3.17.dist-info/top_level.txt
rnow-0.3.17.dist-info/RECORD
