Metadata-Version: 2.4
Name: rnow
Version: 0.3.17
Summary: ReinforceNow CLI - Reinforcement Learning platform command-line interface
Requires-Python: <3.15,>=3.11
License-File: LICENSE
Requires-Dist: click>=8.0.0
Requires-Dist: requests>=2.25.0
Requires-Dist: httpx>=0.24.0
Requires-Dist: pydantic>=2.0.0
Requires-Dist: pyyaml>=5.4.0
Requires-Dist: packaging>=21.0
Requires-Dist: prompt_toolkit>=3.0.0
Requires-Dist: tokenizers>=0.15.0
Requires-Dist: openai-harmony>=0.0.8
Requires-Dist: boto3>=1.28.0
Provides-Extra: test
Requires-Dist: tinker-cookbook>=0.1.0; extra == "test"
Requires-Dist: transformers>=4.40.0; extra == "test"
Provides-Extra: api
Requires-Dist: fastapi>=0.68.0; extra == "api"
Requires-Dist: uvicorn>=0.15.0; extra == "api"
Provides-Extra: mcp
Requires-Dist: fastmcp>=0.1.0; extra == "mcp"
Provides-Extra: all
Requires-Dist: tinker-cookbook>=0.1.0; extra == "all"
Requires-Dist: transformers>=4.40.0; extra == "all"
Requires-Dist: fastapi>=0.68.0; extra == "all"
Requires-Dist: uvicorn>=0.15.0; extra == "all"
Requires-Dist: fastmcp>=0.1.0; extra == "all"
Dynamic: license-file
